brynq_sdk_zenegy/__init__.py
brynq_sdk_zenegy/absence.py
brynq_sdk_zenegy/companies.py
brynq_sdk_zenegy/cost_center.py
brynq_sdk_zenegy/departments.py
brynq_sdk_zenegy/employee_documents.py
brynq_sdk_zenegy/employees.py
brynq_sdk_zenegy/global_value_sets.py
brynq_sdk_zenegy/global_values.py
brynq_sdk_zenegy/paychecks.py
brynq_sdk_zenegy/payroll.py
brynq_sdk_zenegy/payslips.py
brynq_sdk_zenegy/pensions.py
brynq_sdk_zenegy/supplements_and_deductions_rates.py
brynq_sdk_zenegy/zenegy.py
brynq_sdk_zenegy/schemas/__init__.py
brynq_sdk_zenegy/schemas/absences.py
brynq_sdk_zenegy/schemas/companies.py
brynq_sdk_zenegy/schemas/company_cost_centers.py
brynq_sdk_zenegy/schemas/company_departments.py
brynq_sdk_zenegy/schemas/employee_documents.py
brynq_sdk_zenegy/schemas/employee_pay_checks.py
brynq_sdk_zenegy/schemas/employee_pensions.py
brynq_sdk_zenegy/schemas/employees.py
brynq_sdk_zenegy/schemas/global_value_sets.py
brynq_sdk_zenegy/schemas/global_values.py
brynq_sdk_zenegy/schemas/payrolls.py
brynq_sdk_zenegy/schemas/payslips.py
brynq_sdk_zenegy/schemas/supplements_and_deductions_rates.py
brynq_sdk_zenegy-1.3.3.dist-info/METADATA
brynq_sdk_zenegy-1.3.3.dist-info/WHEEL
brynq_sdk_zenegy-1.3.3.dist-info/top_level.txt
brynq_sdk_zenegy-1.3.3.dist-info/RECORD
