Metadata-Version: 2.4
Name: brynq_sdk_zenegy
Version: 1.3.3
Summary: Zenegy wrapper from BrynQ
Author: BrynQ
Author-email: support@brynq.com
License: BrynQ License
Requires-Dist: brynq-sdk-brynq>=3
Dynamic: author
Dynamic: author-email
Dynamic: description
Dynamic: license
Dynamic: requires-dist
Dynamic: summary
